linear_regression_model/__init__.py
linear_regression_model/data_generator.py
linear_regression_model/gradiant_descent.py
linear_regression_model/linear_model.py
linear_regression_package-0.1.dist-info/METADATA
linear_regression_package-0.1.dist-info/WHEEL
linear_regression_package-0.1.dist-info/top_level.txt
linear_regression_package-0.1.dist-info/RECORD
